harpy/__init__.py
harpy/__main__.py
harpy/handlers.py
harpy/logging.conf
harpy/ouis.json
harpy/threads.py
harpy/core/__init__.py
harpy/core/data.py
harpy/core/notice_.py
harpy_prjct-2021.12.22.dist-info/LICENSE
harpy_prjct-2021.12.22.dist-info/METADATA
harpy_prjct-2021.12.22.dist-info/WHEEL
harpy_prjct-2021.12.22.dist-info/entry_points.txt
harpy_prjct-2021.12.22.dist-info/top_level.txt
harpy_prjct-2021.12.22.dist-info/RECORD
