Metadata-Version: 2.1
Name: harpy-prjct
Version: 2021.12.22
Summary: Active/passive ARP discovery tool
Home-page: https://github.com/serhatcelik/harpy
Author: Serhat Çelik
Author-email: prjctsrht@gmail.com
License: MIT
Download-URL: https://github.com/serhatcelik/harpy/releases/latest
Project-URL: Source Code, https://github.com/serhatcelik/harpy
Project-URL: Bug Tracker, https://github.com/serhatcelik/harpy/issues
Project-URL: Documentation, https://github.com/serhatcelik/harpy/wiki
Project-URL: Say Thanks!, https://saythanks.io/to/serhatcelik
Keywords: harpy,arp,discovery
Platform: Linux
Classifier: Development Status :: 5 - Production/Stable
Classifier: Environment :: Console
Classifier: Intended Audience :: Information Technology
Classifier: Intended Audience :: Science/Research
Classifier: License :: OSI Approved :: MIT License
Classifier: Natural Language :: English
Classifier: Operating System :: POSIX
Classifier: Operating System :: POSIX :: Linux
Classifier: Programming Language :: Python :: 2
Classifier: Programming Language :: Python :: 2.7
Classifier: Programming Language :: Python :: 3
Classifier: Programming Language :: Python :: 3.4
Classifier: Programming Language :: Python :: 3.5
Classifier: Programming Language :: Python :: 3.6
Classifier: Programming Language :: Python :: 3.7
Classifier: Programming Language :: Python :: 3.8
Classifier: Programming Language :: Python :: 3.9
Classifier: Programming Language :: Python :: 3.10
Classifier: Topic :: System :: Networking
Classifier: Topic :: System :: Networking :: Monitoring
Requires-Python: >=2.7, !=3.0.*, !=3.1.*, !=3.2.*, !=3.3.*, <4
License-File: LICENSE
